examon_core/__init__.py
examon_core/code_execution/__init__.py
examon_core/code_execution/code_execution_sandbox.py
examon_core/code_execution/unrestricted_driver.py
examon_core/examon.py
examon_core/factories/__init__.py
examon_core/factories/code_to_string.py
examon_core/factories/examon.py
examon_core/factories/hints.py
examon_core/factories/metrics.py
examon_core/factories/multi_choice.py
examon_core/factories/tags.py
examon_core/filter_options.py
examon_core/global_settings.py
examon_core/gof/decorators.py
examon_core/in_memory_db.py
examon_core/metrics/__init__.py
examon_core/metrics/code_analysis_visitor.py
examon_core/metrics/difficulty_categorisor.py
examon_core/metrics/standard_metrics_calculator.py
examon_core/metrics/visit_methods.py
examon_core/models/__init__.py
examon_core/models/code_metrics.py
examon_core/models/python_code_convertor.py
examon_core/models/question.py
examon_core/models/question_response.py
examon_core/protocols/__init__.py
examon_core/protocols/code_decorator.py
examon_core/protocols/code_execution_driver.py
examon_core/protocols/code_metrics.py
examon_core/protocols/difficulty.py
examon_core/protocols/examon.py
examon_core/protocols/function_to_string.py
examon_core/protocols/hints.py
examon_core/protocols/multi_choice.py
examon_core/protocols/question.py
examon_core/protocols/tags.py
examon_core/protocols/unique_id.py
examon_core/serializer.py
examon_core/unique_id_generator.py
examon_core-2.0.4.dist-info/METADATA
examon_core-2.0.4.dist-info/WHEEL
examon_core-2.0.4.dist-info/RECORD
