Metadata-Version: 2.1
Name: examon_core
Version: 2.0.4
Summary: Examon Core Libs
Author: Jarrod Folino
Author-email: jdfolino@icloud.com
Requires-Python: >=3.9
Classifier: Programming Language :: Python :: 3
Classifier: Programming Language :: Python :: 3.9
Classifier: Programming Language :: Python :: 3.10
Classifier: Programming Language :: Python :: 3.11
Classifier: Programming Language :: Python :: 3.12
Requires-Dist: dataclasses-serialization (>=1.3.1,<2.0.0)
Requires-Dist: radon (>=6.0.1,<7.0.0)
